Metadata-Version: 1.1
Name: prontexPack
Version: 0.0.3
Summary: a pack of functions and thing that can be cool in python
Home-page: UNKNOWN
Author: Warren Stevens
Author-email: no@gmail.com
License: MIT
Keywords: pack
Platform: UNKNOWN
Classifier: Development Status :: 5 - Production/Stable
Classifier: Intended Audience :: Developers
Classifier: Operating System :: Microsoft :: Windows :: Windows 10
Classifier: License :: OSI Approved :: MIT License
Classifier: Programming Language :: Python :: 3
